README.md
setup.cfg
setup.py
rnnmorph/__init__.py
rnnmorph/batch_generator.py
rnnmorph/char_embeddings_model.py
rnnmorph/config.py
rnnmorph/model.py
rnnmorph/predictor.py
rnnmorph/settings.py
rnnmorph/tag_genres.py
rnnmorph/test_predictor.py
rnnmorph/train.py
rnnmorph.egg-info/PKG-INFO
rnnmorph.egg-info/SOURCES.txt
rnnmorph.egg-info/dependency_links.txt
rnnmorph.egg-info/requires.txt
rnnmorph.egg-info/top_level.txt
rnnmorph/data_preparation/__init__.py
rnnmorph/data_preparation/converter.py
rnnmorph/data_preparation/grammeme_vectorizer.py
rnnmorph/data_preparation/loader.py
rnnmorph/data_preparation/process_tag.py
rnnmorph/data_preparation/word_form.py
rnnmorph/data_preparation/word_vocabulary.py
rnnmorph/models/en/build_config.json
rnnmorph/models/en/char_set.txt
rnnmorph/models/en/eval_model.h5
rnnmorph/models/en/eval_model.json
rnnmorph/models/en/gram_input.json
rnnmorph/models/en/gram_output.json
rnnmorph/models/en/train_config.json
rnnmorph/models/en/train_model.h5
rnnmorph/models/en/train_model.json
rnnmorph/models/en/word_vocabulary.pickle
rnnmorph/models/ru/build_config.json
rnnmorph/models/ru/char_set.txt
rnnmorph/models/ru/eval_model.h5
rnnmorph/models/ru/eval_model.json
rnnmorph/models/ru/gram_input.json
rnnmorph/models/ru/gram_output.json
rnnmorph/models/ru/train_config.json
rnnmorph/models/ru/train_model.h5
rnnmorph/models/ru/train_model.json
rnnmorph/models/ru/word_vocabulary.pickle
rnnmorph/util/__init__.py
rnnmorph/util/embeddings.py
rnnmorph/util/timeit.py
rnnmorph/util/tqdm_open.py