Metadata-Version: 1.1
Name: rnnmorph
Version: 0.4.1
Summary: RNNMorph: neural network disambiguation of pymorphy2 parses for precise POS-tagging in Russian language.
Home-page: https://github.com/IlyaGusev/rnnmorph
Author: Ilya Gusev
Author-email: phoenixilya@gmail.com
License: UNKNOWN
Download-URL: https://github.com/IlyaGusev/rnnmorph/archive/0.4.1.tar.gz
Keywords: nlp,russian,lstm,morphology
Platform: UNKNOWN
Classifier: Development Status :: 4 - Beta
Classifier: Intended Audience :: Developers
Classifier: Topic :: Text Processing :: Linguistic
Classifier: License :: OSI Approved :: Apache Software License
Classifier: Natural Language :: Russian
Classifier: Programming Language :: Python :: 3.5
Classifier: Programming Language :: Python :: 3.6
Classifier: Programming Language :: Python :: 3.7
Classifier: Programming Language :: Python :: 3.8
Classifier: Programming Language :: Python :: 3.9
